setup.py
django_flows.egg-info/PKG-INFO
django_flows.egg-info/SOURCES.txt
django_flows.egg-info/dependency_links.txt
django_flows.egg-info/requires.txt
django_flows.egg-info/top_level.txt
flows/__init__.py
flows/appconfig.py
flows/binder.py
flows/components.py
flows/config.py
flows/handler.py
flows/history.py
flows/models.py
flows/preconditions.py
flows/transitions.py
flows/additional/__init__.py
flows/additional/crispy.py
flows/additional/celery/__init__.py
flows/additional/celery/cleanup_task.py
flows/management/__init__.py
flows/management/commands/__init__.py
flows/management/commands/cleanupflows.py
flows/south_migrations/0001_initial.py
flows/south_migrations/0002_auto__add_field_statemodel_last_access.py
flows/south_migrations/__init__.py
flows/statestore/__init__.py
flows/statestore/base.py
flows/statestore/django_store.py
flows/statestore/redis_store.py
flows/statestore/tmpfile_store.py