Metadata-Version: 1.1
Name: django-flows
Version: 1.3
Summary: django-flows keeps state and position in complicated flows of logic, allowing optional branches and complicated paths through a series of individual user actions.
Home-page: https://github.com/carlio/django-flows
Author: Carl Crowder
Author-email: django-flows@carlcrowder.com
License: BSD
Keywords: django
Platform: UNKNOWN
Classifier: Development Status :: 5 - Production/Stable
Classifier: Environment :: Web Environment
Classifier: Framework :: Django
Classifier: Intended Audience :: Developers
Classifier: License :: OSI Approved :: BSD License
Classifier: Programming Language :: Python :: 2.7
